.bumbversion.cfg
.gitignore
MANIFEST.in
Makefile
README.md
TODO.txt
demos.sh
pypackage.mk
requirements.txt
setup.py
tests.sh
tests_with_coverage.sh
.circleci/config.yml
docs/.gitignore
docs/Makefile
docs/README.txt
docs/docs.mk
docs/epydoc.cfg
docs/gitadd.zsh
docs/sphinxtogithub.py
docs/source/api.rst
docs/source/conf.py
docs/source/download.html
docs/source/guide.rst
docs/source/index.rst
docs/source/tutorial.rst
docs/source/why.rst
docs/source/my_static/analytics.js
docs/source/my_static/custom.css
docs/source/my_static/dummy
docs/source/my_static/generic.css
docs/source/my_templates/layout.html
src/reprep/__init__.py
src/reprep/config.py
src/reprep/constants.py
src/reprep/datanode.py
src/reprep/figure.py
src/reprep/helpers.py
src/reprep/interface.py
src/reprep/mpl.py
src/reprep/node.py
src/reprep/repcontracts.py
src/reprep/structures.py
src/reprep/table.py
src/reprep.egg-info/PKG-INFO
src/reprep.egg-info/SOURCES.txt
src/reprep.egg-info/dependency_links.txt
src/reprep.egg-info/entry_points.txt
src/reprep.egg-info/not-zip-safe
src/reprep.egg-info/requires.txt
src/reprep.egg-info/top_level.txt
src/reprep/demos/__init__.py
src/reprep/demos/colormaps.py
src/reprep/demos/demo_tests.py
src/reprep/demos/figures.py
src/reprep/demos/manager.py
src/reprep/demos/report_layout.py
src/reprep/demos/spines.py
src/reprep/demos/table.py
src/reprep/graphics/__init__.py
src/reprep/graphics/conversions.py
src/reprep/graphics/conversions_tests.py
src/reprep/graphics/filter_colormap.py
src/reprep/graphics/filter_posneg.py
src/reprep/graphics/filter_posneg_test.py
src/reprep/graphics/filter_scale.py
src/reprep/graphics/numpy_utils.py
src/reprep/graphics/scaling.py
src/reprep/graphics/success.py
src/reprep/graphics/zoom.py
src/reprep/output/__init__.py
src/reprep/output/html.py
src/reprep/output/html_test.py
src/reprep/output/hdf/__init__.py
src/reprep/output/hdf/hdf1_rawdata.py
src/reprep/output/hdf/hdf1_read.py
src/reprep/output/hdf/hdf1_write.py
src/reprep/output/hdf/hdf_read.py
src/reprep/output/hdf/test_hdf.py
src/reprep/output/ipn/__init__.py
src/reprep/output/ipn/node.py
src/reprep/plot_utils/__init__.py
src/reprep/plot_utils/axes.py
src/reprep/plot_utils/spines.py
src/reprep/plot_utils/styles.py
