Metadata-Version: 1.1
Name: reprep
Version: 2.11.0
Summary: Reproducible Reports
Home-page: http://AndreaCensi.github.com/reprep/
Author: Andrea Censi
Author-email: censi@mit.edu
License: LGPL
Download-URL: http://github.com/AndreaCensi/reprep/tarball/2.11.0
Keywords: report reproducible research tables html latex
Platform: UNKNOWN
